kairoz/__init__.py
kairoz/client.py
kairoz/openai.py
kairoz/prompt.py
kairoz/providers.py
kairoz/tracking.py
kairoz/version.py
kairoz-0.1.3.dist-info/METADATA
kairoz-0.1.3.dist-info/WHEEL
kairoz-0.1.3.dist-info/licenses/LICENSE
kairoz-0.1.3.dist-info/RECORD
