Metadata-Version: 2.4
Name: kairoz
Version: 0.1.3
Summary: SDK for the Kairoz API
Author: Felipe Cañas, Francisco Giovanni Borgogno
License-Expression: MIT
License-File: LICENSE
Classifier: Operating System :: OS Independent
Classifier: Programming Language :: Python :: 3
Requires-Python: >=3.8
Requires-Dist: openai>=1.0.0
Requires-Dist: requests>=2.0.0
Provides-Extra: dev
Requires-Dist: pytest>=8.0.0; extra == 'dev'
